idealforms/__about__.py
idealforms/__init__.py
idealforms/bar.py
idealforms/formatters.py
idealforms/pie.py
idealforms-0.0.14.dist-info/METADATA
idealforms-0.0.14.dist-info/WHEEL
idealforms-0.0.14.dist-info/licenses/LICENSE
idealforms-0.0.14.dist-info/RECORD
