Metadata-Version: 2.1
Name: idealforms
Version: 0.0.14
Summary: Some charts I prepared earlier
Project-URL: Homepage, https://github.com/ilmcconnell/idealforms
Project-URL: Bug Tracker, https://github.com/ilmcconnell/idealforms/issues
Author-email: Iain McConnell <buckler_08_matador@icloud.com>
License-File: LICENSE
Classifier: License :: OSI Approved :: MIT License
Classifier: Operating System :: OS Independent
Classifier: Programming Language :: Python :: 3
Requires-Python: >=3.9
Requires-Dist: matplotlib>=3.5
Requires-Dist: numpy>=1.21
Provides-Extra: tests
Requires-Dist: flake8>=3.9; extra == 'tests'
Requires-Dist: mock>=4.0; extra == 'tests'
Requires-Dist: mypy>=0.910; extra == 'tests'
Requires-Dist: pytest-cov>=2.0; extra == 'tests'
Requires-Dist: pytest>=6.0; extra == 'tests'
Requires-Dist: tox>=3.24; extra == 'tests'
